[
    {
        "name" : "admin",
        "username" : "admin",
        "password" : "1",
        "address" : "0x0",
        "city" : "The Matrix",
        "zipcode" : "0000",
        "isAdmin" : true
    },
    {
        "name" : "Bart Goethals",
        "username" : "bgoethals",
        "password" : "topsecret",
        "address" : "De G.10",
        "city" : "Antwerpen",
        "zipcode" : "2000",
        "isAdmin" : false
    },
    {
        "name" : "Jon Sneyers",
        "username" : "jonsneyers",
        "password" : "topsecret",
        "address" : "UAntwerpen",
        "city" : "Antwerpen",
        "zipcode" : "2000",
        "isAdmin" : false
    },
    {
        "name" : "Len Feremans",
        "username" : "lilferemans",
        "password" : "topsecret",
        "address" : "UAntwerpen",
        "city" : "Antwerpen",
        "zipcode" : "2000",
        "isAdmin" : false
    },
    {
        "name" : "Benny Van Houdt",
        "username" : "bennyvh",
        "password" : "topsecret",
        "address" : "UAntwerpen",
        "city" : "Houdt",
        "zipcode" : "2001",
        "isAdmin" : false
    },
    {
        "name" : "Hans Van Gheluwe",
        "username" : "hans",
        "password" : "topsecret",
        "address" : "UAntwerpen",
        "city" : "Antwerpen",
        "zipcode" : "2000",
        "isAdmin" : false
    }
]
